Workbook
Name C_C: parameters!$H$3
Name cycle_length: parameters!$H$51
Name fracinfected: parameters!#REF!
Name U_I: parameters!$H$96
Name U_S: parameters!$H$87

Sheet Readme

Sheet Inputs Table >>

Sheet parameters
B1: Category | C1: Parameter | D1: Definition | E1: Currency | F1: Year | G1: Value | H1: Lower | I1: Upper | J1: Distribution | K1: Source | L1: Comments
D2: General
B3: Cohort | C3: n_cohort | D3: Cohort size | E3: NA | F3: NA | G3: 1000 | H3: NA | I3: NA | J3: NA | K3: Assumption
B4: Time | C4: cycle_length_days | D4: Cycle length, days | E4: NA | F4: NA | G4: 7 | H4: NA | I4: NA | J4: NA | K4: Assumption
B5: Time | C5: time_horizon_years | D5: Analytic time horizon, years | E5: NA | F5: NA | G5: 10 | H5: 1 | I5: 20 | J5: NA | K5: Assumption
B6: Simulations | C6: n_boot_samps | D6: Number of bootstrap samples | E6: NA | F6: NA | G6: 1000 | H6: NA | I6: NA | J6: NA | K6: Assumption
B7: Demographics | C7: Mean_age | D7: Mean age of working age population, 15-64 years | E7: NA | F7: NA | G7: 38 | H7: 15 | I7: 64 | J7: Gamma | K7: https://agenciadenoticias.ibge.gov.br/en/agencia-news/2184-news-agency/news/38187-2022-census-number-of-elderly-persons-in-the-brazilian-population-grew-57-4-in-12-years
B8: Epidemic | D8: Epidemic Parameters
B9: Epidemic | C9: total_inf_cases | D9: Total cases | E9: NA | F9: NA | G9: 425773 | H9: =_xlfn.CHISQ.INV(0.025,2*G9)/2 -> 424495.05 | I9: =_xlfn.CHISQ.INV(0.975,2*(G9-1))/2 -> 427051.85 | J9: Chi-square | K9: Health Information Platform of the Americas (PLISA). Data reported by the Ministries and Institutes of Health of the countries and territories of the Region: https://www.paho.org/en/arbo-portal/chikungunya-data-and-analysis/chikungunya-analysis-country | L9: Rates are per 100,000 populations
B10: Epidemic | C10: base_population | D10: Implied population | E10: NA | F10: NA | G10: =G9/(200.84/100000) -> 2.1199612e+08 | H10: NA | I10: NA | J10: NA | K10: Health Information Platform of the Americas (PLISA). Data reported by the Ministries and Institutes of Health of the countries and territories of the Region: https://www.paho.org/en/arbo-portal/chikungunya-data-and-analysis/chikungunya-analysis-country | L10: Rates are per 100,000 populations
B11: Epidemic | C11: R0 | D11: Basic reproduction number | E11: NA | F11: NA | G11: 3.4 | H11: 2.4 | I11: 4.2 | J11: Gamma | K11: Haider et al, 2020
B12: Epidemic | C12: xi | D12: Behavioural response factor | E12: NA | F12: NA | G12: 1 | H12: =G12*(1-0.05) -> 0.95 | I12: =G12*(1+0.05) -> 1.05 | J12: PERT | K12: Assumption
B13: Epidemic | C13: lambda_days | D13: Incubation period, days | E13: NA | F13: NA | G13: 5 | H13: 1 | I13: 12 | J13: Gamma | K13: https://www.cdc.gov/yellow-book/hcp/travel-associated-infections-diseases/chikungunya.html | L13: Assuming incubation period is 5 days so 0.2 per day
B14: Epidemic | C14: gamma_days | D14: Average duration of infection, days | E14: NA | F14: NA | G14: 8.5 | H14: 7 | I14: 10 | J14: Gamma | K14: https://www.cdc.gov/yellow-book/hcp/travel-associated-infections-diseases/chikungunya.html | L14: Assumes recovery in 7-10 days, 8.5 days as midpoint.
B15: Epidemic | C15: rho_year | D15: Proportion of patients with CCA after 12 months of infection | E15: NA | F15: NA | G15: 0.521 | H15: 0.445 | I15: 0.597 | J15: Gamma | K15: Bertolotti et al, 2020
B16: Epidemic | C16: prop_hosp | D16: Proportion of patients hospitalized | E16: NA | F16: NA | G16: 0.018 | H16: =(1-0.25)*G16 -> 0.0135 | I16: =(1+0.25)*G16 -> 0.0225 | J16: Beta | K16: de Andrade, et al. 2022 | L16: de Andrade quotes 1.8% hospitalization. Gonçalves quotes 0.67% (256/38830)
B17: Epidemic | C17: delta_hosp_10years | D17: CHIKV case-fatality rate, hospitalized patients | E17: NA | F17: NA | G17: =(84+1)/(7337+84+2) -> 0.011450896 | H17: =_xlfn.BETA.INV(0.025, 84+1, 7337+84-84+1) -> 0.0091577628 | I17: =_xlfn.BETA.INV(0.975, 84+1, 7337+84-84+1) -> 0.013993176 | J17: Beta | K17: Pedi et al. 2025 | L17: Total column in Table 3: https://pmc.ncbi.nlm.nih.gov/articles/PMC12407205/pdf/25-0554.pdf
B18: Epidemic | C18: deaths_CHIKV_pop | D18: CHIKV deaths, general population, 2017 | E18: NA | F18: NA | G18: 250 | H18: =_xlfn.CHISQ.INV(0.025,2*G18)/2 -> 219.968 | I18: =_xlfn.CHISQ.INV(0.975,2*(G18-1))/2 -> 280.8637 | J18: Chi-square | K18: Vidal et al. 2021 | L18: https://onlinelibrary.wiley.com/doi/10.1111/tmi.13711
B19: Epidemic | C19: CHIKV_pop | D19: Implied population | E19: NA | F19: NA | G19: =+G18*100000/1.2 -> 20833333 | H19: NA | I19: NA | J19: NA | K19: Vidal et al. 2021 | L19: https://onlinelibrary.wiley.com/doi/10.1111/tmi.13711
B20: Epidemic | C20: seroresponse_placebo_IXCHIQ_180_days | D20: Vaccine efficacy rate for placebo group at 180 days, IXCHIQ | E20: NA | F20: NA | G20: 0 | H20: 0 | I20: 0.053 | J20: Beta | K20: Schneider et al, 2023 | L20: 18-64 years; 180 days after vaccination (Supplementary Table 3)
B21: Epidemic | C21: seroresponse_treatment_IXCHIQ_180_days | D21: Vaccine efficacy rate for treatment group at 180 days, IXCHIQ | E21: NA | F21: NA | G21: 0.984 | H21: 0.953 | I21: 0.997 | J21: Beta | K21: Schneider et al, 2023 | L21: 18-64 years; 180 days after vaccination (Supplementary Table 3)
B22: Epidemic | C22: seroprotection_VIMKUNYA_183_days | D22: Vaccine efficacy rate at 183 days, VIMKUNYA | E22: NA | F22: NA | G22: 0.84 | H22: 0.817 | I22: 0.856 | J22: Beta | K22: Richardson et al., 2025 | L22: seroresponse, Table 2
B23: Epidemic | C23: zeta | D23: Immunogenicity atenuation factor | E23: NA | F23: NA | G23: 0.8 | H23: 0.7 | I23: 1 | J23: NA | K23: Assumption
B24: Epidemic | C24: prop_severe_vse_IXCHIQ | D24: Proportion of severe adverse events IXCHIQ | E24: NA | F24: NA | G24: =58/3082 -> 0.018818949 | H24: =_xlfn.BETA.INV(0.025, 58, 3082-58+1) -> 0.014320248 | I24: =_xlfn.BETA.INV(0.975, 58+1, 3082-58) -> 0.024260663 | J24: Beta | K24: Schneider M et a., 2023 | L24: Confidence intervals are two-sided exact Clopper–Pearson 95% confidence intervals.
B25: Epidemic | C25: prop_severe_vse_VIMKUNYA | D25: Proportion of severe adverse events VIMKUNYA | E25: NA | F25: NA | G25: =73/2790 -> 0.026164875 | H25: =_xlfn.BETA.INV(0.025, 73, 2790-73+1) -> 0.020563875 | I25: =_xlfn.BETA.INV(0.975, 73+1, 2790-73) -> 0.032787184 | J25: Beta | K25: Richardson et al., 2025 | L25: Greater or equal grade 3 (Table 3); Confidence intervals are two-sided exact Clopper–Pearson 95% confidence intervals.
B26: Epidemic | C26: prop_serious_vse_IXCHIQ | D26: Proportion of serious adverse events IXCHIQ | E26: NA | F26: NA | G26: =2/3082 -> 0.00064892927 | H26: =_xlfn.BETA.INV(0.025, 2, 3082-2+1) -> 7.8598009e-05 | I26: =_xlfn.BETA.INV(0.975, 2+1, 3082-2) -> 0.0023421695 | J26: Beta | K26: Schneider M et a., 2023 | L26: Only two serious adverse events were considered related to VLA1553 treatment (one mild myalgia and one syndrome of inappropriate antidiuretic hormone secretion). Both participants recovered fully.
B27: Epidemic | C27: prop_serious_vse_VIMKUNYA | D27: Proportion of serious adverse events VIMKUNYA | E27: NA | F27: NA | G27: =(23-1)/2790 -> 0.0078853047 | H27: =_xlfn.BETA.INV(0.025, 23-1, 2790-(23-1)+1) -> 0.0049480848 | I27: =_xlfn.BETA.INV(0.975, 73+1, 2790-73) -> 0.032787184 | J27: Beta | K27: Richardson et al., 2025 | L27: Confidence intervals are two-sided exact Clopper–Pearson 95% confidence intervals.
B28: Epidemic | C28: psi_stated | D28: 3-weeks vaccination rate | E28: NA | F28: NA | G28: 0.55 | H28: 0.51 | I28: 0.7 | J28: PERT | K28: Assumption | L28: Manaquin R, Desmoulin A, Luong Nguyen LB, et al. Acceptance of chikungunya vaccination: a rapid survey in Reunion island during an epidemic. Vaccine. 2025/10/03/ 2025;64:127720. doi:https://doi.org/10.1016/j.vaccine.2025.127720 40. World Health Organization. Chikungunya - La Réunion and Mayotte. WHO. December 11, 2025. Updated May 12, 2025. Accessed December 11, 2025. https://www.who.int/emergencies/disease-outbreak-news/item/2025-DON567 41. Curren EJ, Ellis EM, Hennessey MJ, Delorey MJ, Fischer M, Staples JE. Acceptability of a Chikungunya Virus Vaccine, United States Virgin Islands. Am J Trop Med Hyg. Feb 1 2023;108(2):363-365. doi:10.4269/ajtmh.22-0429 42. Quenard F, Pecout F, Barry TA, et al. Acceptability of a chikungunya vaccine and dengue vaccine among travelers in Martinique (French West Indies), for the travel and for their home territory. IJID Reg. Dec 2025;17:100791. doi:10.1016/j.ijregi.2025.100791
B29: Epidemic | C29: phi | D29: Realization factor for vaccination | E29: NA | F29: NA | G29: 0.6 | H29: 0.4 | I29: 0.75 | J29: PERT | K29: Assumption
B30: Epidemic | C30: omicron | D30: IXCHQ preference weight | E30: NA | F30: NA | G30: 1 | H30: 0.5 | I30: 1.5 | J30: PERT | K30: Assumption
B31: Epidemic | C31: pi_VIMKUNYA_vs_IXCHIQ | D31: VIMKUNYA preference weight, relative to IXCHIQ | E31: NA | F31: NA | G31: 1 | H31: 0.5 | I31: 1.2 | J31: PERT | K31: Assumption
B32: Epidemic | C32: theta_IXCHIQ_days | D32: Vaccine daily waning rate, IXCHIQ | E32: NA | F32: NA | G32: 2.640161e-05 | H32: 0 | I32: 6.943443e-05 | J32: Lognormal | K32: Calculated from McMahon, R., Toepfer, S., Sattler, N., et al. Antibody persistence and safety of a live-attenuated chikungunya virus vaccine up to 2 years after single-dose administration in adults in the USA: a single-arm, multicentre, phase 3b study. Lancet Infectious Diseases. 2024;24(12):1383–1392. | L32: See Appendix
B33: Epidemic | C33: theta_VIMKUNYA_days | D33: Vaccine daily waning rate, VIMKUNYA | E33: NA | F33: NA | G33: 0.0008298682 | H33: 0.0006795308 | I33: 0.0009955332 | J33: Lognormal | K33: Calculated from Richardson et al. | L33: See Appendix
B34: Epidemic | C34: kappa_days | D34: Average duration of chronic disease, days | E34: NA | F34: NA | G34: 365 | H34: =(1/3)*G34 -> 121.66667 | I34: =2*G34 -> 730 | J34: Gamma | K34: Paixao 2018 | L34: Assume patients recover from the chronic form of disease in 12 months
B35: Utilities | D35: Utilities
B36: Utilities | C36: qol_S | D36: Susceptible | E36: NA | F36: NA | G36: 0.824 | H36: =G36 - _xlfn.T.INV.2T(0.05, 5774-1) * (0.172 / SQRT(5774)) -> 0.81956259 | I36: =G36 + _xlfn.T.INV.2T(0.05, 5774-1) * (0.172 / SQRT(5774)) -> 0.82843741 | J36: Beta | K36: Santos M, et al. 2021
B37: Utilities | C37: qol_D | D37: Death | E37: NA | F37: NA | G37: 0 | H37: NA | I37: NA | J37: NA | K37: Assumption
B38: Utilities | C38: qol_I_factor | D38: Infectious (acute CHIKV) utility multiplier | E38: NA | F38: NA | G38: =0.803 -> 0.803 | H38: =0.72 -> 0.72 | I38: =0.875 -> 0.875 | J38: Beta | K38: Shim E, et al. 2017 | L38: Assume utilities in infection similar to Dengue
B39: Utilities | C39: qol_E_factor | D39: Exposed (latent) utility multiplier | E39: NA | F39: NA | G39: =0.85 -> 0.85 | H39: =MAX((1-0.25)*G39, 0) -> 0.6375 | I39: =MIN(1, (1+0.25)*G39) -> 1 | J39: Beta | K39: Assumption | L39: Assuming same SD from Santos M, et al. 2021
B40: Utilities | C40: qol_C_factor | D40: Chronic Disease (persistent polyarthritis) utility multiplier | E40: NA | F40: NA | G40: =0.6 -> 0.6 | H40: =G40-((0.19)/SQRT(315))*_xlfn.T.INV.2T(0.05, 315-1) -> 0.57893684 | I40: =G40+((0.19)/SQRT(315))*_xlfn.T.INV.2T(0.05, 315-1) -> 0.62106316 | J40: Beta | K40: Linde L, et al. 2013 | L40: SD = 0.19, assuming utility Rheumatoid Arthritis = utility in chronic phase; N = 315
B41: Utilities | C41: qol_I_acute_usa | D41: Utility weight from accute disease, not hospitalized | E41: NA | F41: NA | G41: 0.63 | H41: 0.19 | I41: 0.91 | J41: PERT | K41: refs 55-58 | L41: https://pmc.ncbi.nlm.nih.gov/articles/PMC12304215/pdf/41541_2025_Article_1194.pdf | M41: USA population
B42: Utilities | C42: qol_loss_severe_vae_usa | D42: Disutilities from severe vaccine adverse events | E42: NA | F42: NA | G42: 0.002 | H42: 0 | I42: 0.053 | J42: PERT | K42: Refs 37, 42 | L42: https://pmc.ncbi.nlm.nih.gov/articles/PMC12304215/pdf/41541_2025_Article_1194.pdf | M42: USA population
B43: Utilities | C43: qol_loss_serious_vae_usa | D43: Disutilities from serious vaccine adverse events | E43: NA | F43: NA | G43: 0.076 | H43: 0.054 | I43: 1 | J43: PERT | K43: Refs 37, 59 | L43: https://pmc.ncbi.nlm.nih.gov/articles/PMC12304215/pdf/41541_2025_Article_1194.pdf | M43: Schneider, M. et al. Safety and immunogenicity of a single-shot liveattenuated chikungunya vaccine: a double-blind, multicentre, randomised, placebo-controlled, phase 3 trial. Lancet 401, 2138–2147 (2023). Prosser, L. A. et al. Effects of adverse events on the projected population benefits and cost-effectiveness of using live attenuated influenza vaccine in children aged 6 months to 4 years. Arch. Pediatr. Adolesc. Med. 165, 112–118 (2011). | N43: Hospitalization following vaccination; USA population
B44: Costs | D44: Costs
B45: Costs | D45: Vaccination Costs | H45: =G49/G48 -> 1.25
B46: Costs | C46: C_IXCHIQ_Dose_public | D46: IXCHIQ dose price cap, public sector (18% average tax rate) | E46: BRL | F46: 2025 | G46: =chiqx_price!$I$10 -> 929.12 | H46: =chiqx_price!$I$9 -> 761.88 | I46: =chiqx_price!$I$11 -> 989.45 | J46: Gamma | K46: CMED (https://www.gov.br/anvisa/pt-br/assuntos/medicamentos/cmed/precos) | L46: Based on average tax rate of 18% | M46: Sarmento T, et al. 2022 describes WTP of $31.17. Dengue vaccine in Brazil costs $70-100. YF vaccine costs $50. In the US, CHIKV vaccine costs $300-450, dengue vaccine costs $66, YF vaccine $205-235
B47: Costs | C47: C_IXCHIQ_Dose_private | D47: IXCHIQ dose price cap, private sector (18% average tax rate) | E47: BRL | F47: 2025 | G47: =chiqx_price!$J$10 -> 1246.38 | H47: =chiqx_price!$J$9 -> 1022.03 | I47: =chiqx_price!$J$11 -> 1327.31 | J47: Gamma | K47: CMED (https://www.gov.br/anvisa/pt-br/assuntos/medicamentos/cmed/precos) | L47: Based on average tax rate of 18% | M47: Sarmento T, et al. 2022 describes WTP of $31.17. Dengue vaccine in Brazil costs $70-100. YF vaccine costs $50. In the US, CHIKV vaccine costs $300-450, dengue vaccine costs $66, YF vaccine $205-235
B48: Costs | C48: C_IXCHIQ_Dose_usa | D48: IXCHIQ dose cost, USA | E48: USD | F48: 2025 | G48: 209 | H48: 160 | I48: 275 | J48: Triangular | K48: https://pmc.ncbi.nlm.nih.gov/articles/PMC12304215/pdf/41541_2025_Article_1194.pdf
B49: Costs | C49: C_VIMKUNYA_Dose_usa | D49: VIMKUNYA dose cost, USA | E49: USD | F49: 2025 | G49: =+(G48/I48)*I49 -> 261.25 | H49: =+(H48/I48)*I49 -> 200 | I49: 343.75 | J49: Triangular | K49: https://medicaid.ms.gov/wp-content/uploads/2025/06/Vaccines-Covered-Through-Pharmacy-Billing.pdf
B50: Costs | C50: eta | D50: Ratio of actual price to vaccine price cap | E50: NA | F50: NA | G50: 0.5 | H50: 0 | I50: 0.75 | J50: PERT | K50: Assumption | L50: Based on QDENGA and Pneumo-13 pricing
B51: Costs | C51: Wastage_Rate | D51: Vaccine wastage rate | E51: NA | F51: NA | G51: 0.1 | H51: 0.05 | I51: 0.15 | J51: PERT | K51: Durand et al., 2017 | L51: From Dengue CEA
B52: Costs | C52: C_Vaccine_Admin | D52: Administration cost | E52: BRL | F52: 2016 | G52: 7.3 | H52: =(1-0.25)*G52 -> 5.475 | I52: =(1+0.25)*G52 -> 9.125 | J52: Gamma | K52: Durand et al., 2017 | L52: Durand report cost in 2016 Brazilian Real of 7.3 to administer 1 dose Dengue
B53: Costs | D53: Direct Costs
B54: Costs | C54: hosp_LOS_days | D54: Average hospitalization LOS, days | E54: NA | F54: NA | G54: 10.85 | H54: =(1-0.25)*G54 -> 8.1375 | I54: =(1+0.25)*G54 -> 13.5625 | J54: Gamma | K54: de Andrade, et al. 2022 | L54: 2017 dollars: $1 to $1.31 for 2025 dollars
B55: Costs | C55: pub_share_ip_admissions | D55: Public share of inpatient admissions | E55: NA | F55: NA | G55: 0.75 | H55: =(1-0.25)*G55 -> 0.5625 | I55: =(1+0.25)*G55 -> 0.9375 | J55: Beta | K55: Ref 31 | L55: https://pmc.ncbi.nlm.nih.gov/articles/PMC12304215/pdf/41541_2025_Article_1194.pdf | M55: <<-- Check ref
B56: Costs | C56: C_inpatient_stay_public | D56: Average inpatient stay cost, public sector | E56: BRL | F56: 2019 | G56: 347.37 | H56: =(1-0.25)*G56 -> 260.5275 | I56: =(1+0.25)*G56 -> 434.2125 | J56: Gamma | K56: Gonçalves, et al. 2024
B57: Costs | C57: C_inpatient_stay_private | D57: Average inpatient stay cost, private sector | E57: BRL | F57: 2019 | G57: 2474.05 | H57: =(1-0.25)*G57 -> 1855.5375 | I57: =(1+0.25)*G57 -> 3092.5625 | J57: Gamma | K57: Gonçalves, et al. 2024
B58: Costs | C58: C_outpatient_visit | D58: Medical appointment cost (15 min) | E58: BRL | F58: 2019 | G58: 23.17 | H58: =(1-0.25)*G58 -> 17.3775 | I58: =(1+0.25)*G58 -> 28.9625 | J58: Gamma | K58: Gonçalves, et al. 2024
B59: Costs | D59: Acute phase
B60: Costs | C60: n_reported_cases_acute | D60: Total number of reported cases in acute phase | E60: NA | F60: 2019 | G60: 38830 | H60: =(1-0.25)*G60 -> 29122.5 | I60: =(1+0.25)*G60 -> 48537.5 | J60: Gamma | K60: Gonçalves, et al. 2024
B61: Costs | C61: n_outpatient_visit_acute | D61: Number of outpatient visits during the acute phase | E61: NA | F61: NA | G61: 2 | H61: NA | I61: NA | J61: NA | K61: Assumption | L61: Once every 7 days (Table 2)
B62: Costs | C62: minor_moderate_share_acute | D62: Share of acute phase cases with minor/moderate pain | E62: NA | F62: NA | G62: 0.47 | H62: =(1-0.25)*G62 -> 0.3525 | I62: =(1+0.25)*G62 -> 0.5875 | J62: Beta | K62: Gonçalves, et al. 2024; Delgado-Enciso I, Paz-Michel B, Melnikov V, Guzman-Esquivel J, Espinoza-Gomez F, Soriano-Hernandez AD, et al. Smoking and female sex as key risk factors associated with severe arthralgia in acute and chronic phases of Chikungunya virus infection. Exp Ther Med 2018; 15(3): 2634-42. https://doi.org/10.3892/etm.2017.5668 [DOI] [PMC free article] [PubMed]
B63: Costs | C63: minor_moderate_pain_rx_days | D63: Duration of minor/moderate pain treatment, days | E63: NA | F63: NA | G63: 7 | H63: NA | I63: NA | J63: NA | K63: Gonçalves, et al. 2024
B64: Costs | C64: C_dipyrone | D64: Dipyrone (for minor/moderate pain treatment) | E64: BRL | F64: 2019 | G64: 4.33 | H64: =(1-0.25)*G64 -> 3.2475 | I64: =(1+0.25)*G64 -> 5.4125 | J64: Gamma | K64: Gonçalves, et al. 2024
B65: Costs | C65: C_acetaminophen | D65: Acetaminophen (for minor/moderate pain treatment) | E65: BRL | F65: 2019 | G65: 1.13 | H65: =(1-0.25)*G65 -> 0.8475 | I65: =(1+0.25)*G65 -> 1.4125 | J65: Gamma | K65: Gonçalves, et al. 2024
B66: Costs | C66: severe_pain_rx_days | D66: Duration of severe pain treatment, days | E66: NA | F66: NA | G66: 7 | H66: NA | I66: NA | J66: NA | K66: Gonçalves, et al. 2024
B67: Costs | C67: C_tramadol | D67: Tramadol (for severe pain treatment) | E67: BRL | F67: 2019 | G67: 4.24 | H67: =(1-0.25)*G67 -> 3.18 | I67: =(1+0.25)*G67 -> 5.3 | J67: Gamma | K67: Gonçalves, et al. 2024
B68: Costs | C68: C_codeine | D68: Codeine (for severe pain treatment) | E68: BRL | F68: 2019 | G68: 20.95 | H68: =(1-0.25)*G68 -> 15.7125 | I68: =(1+0.25)*G68 -> 26.1875 | J68: Gamma | K68: Gonçalves, et al. 2024
B69: Costs | C69: C_oxycodone | D69: Oxycodone (for severe pain treatment) | E69: BRL | F69: 2019 | G69: 89.33 | H69: =(1-0.25)*G69 -> 66.9975 | I69: =(1+0.25)*G69 -> 111.6625 | J69: Gamma | K69: Gonçalves, et al. 2024
B70: Costs | D70: Post-acute phase
B71: Costs | C71: n_reported_cases_postacute | D71: Total number of reported cases in post-acute phase | E71: NA | F71: 2019 | G71: 20852 | H71: =(1-0.25)*G71 -> 15639 | I71: =(1+0.25)*G71 -> 26065 | J71: Gamma | K71: Gonçalves, et al. 2024
B72: Costs | C72: n_outpatient_visit_postacute | D72: Number of outpatient visits during the post-acute phase | E72: NA | F72: NA | G72: 3 | H72: NA | I72: NA | J72: NA | K72: Assumption | L72: Once every 4 weeks (Table 3)
B73: Costs | C73: arthritis_share_postacute | D73: Share of post-acute phase cases with arthritis | E73: NA | F73: NA | G73: 0.755 | H73: =(1-0.25)*G73 -> 0.56625 | I73: =(1+0.25)*G73 -> 0.94375 | J73: Beta | K73: Gonçalves, et al. 2024; Delgado-Enciso I, Paz-Michel B, Melnikov V, Guzman-Esquivel J, Espinoza-Gomez F, Soriano-Hernandez AD, et al. Smoking and female sex as key risk factors associated with severe arthralgia in acute and chronic phases of Chikungunya virus infection. Exp Ther Med 2018; 15(3): 2634-42. https://doi.org/10.3892/etm.2017.5668 [DOI] [PMC free article] [PubMed]
B74: Costs | C74: C_prednisone | D74: Cost of prednisone (for arthritis treatment) | E74: BRL | F74: 2019 | G74: 16.28 | H74: =(1-0.25)*G74 -> 12.21 | I74: =(1+0.25)*G74 -> 20.35 | J74: Gamma | K74: Gonçalves, et al. 2024 | L74: 8-weeks treatment course
B75: Costs | C75: C_ibuprofen | D75: Cost of ibuprofen (for treatment of nerve pain/pain without arthritis) | E75: BRL | F75: 2019 | G75: 16.1 | H75: =(1-0.25)*G75 -> 12.075 | I75: =(1+0.25)*G75 -> 20.125 | J75: Gamma | K75: Gonçalves, et al. 2024 | L75: 4-weeks treatment course
B76: Costs | C76: C_amitriptyline | D76: Cost of amitriptyline (for treatment of nerve pain/pain without arthritis) | E76: BRL | F76: 2019 | G76: 1.06 | H76: =(1-0.25)*G76 -> 0.795 | I76: =(1+0.25)*G76 -> 1.325 | J76: Gamma | K76: Gonçalves, et al. 2024 | L76: 2-weeks treatment course
B77: Costs | C77: C_gabapentin | D77: Cost of gabapentin (for treatment of nerve pain/pain without arthritis) | E77: BRL | F77: 2019 | G77: 9.16 | H77: =(1-0.25)*G77 -> 6.87 | I77: =(1+0.25)*G77 -> 11.45 | J77: Gamma | K77: Gonçalves, et al. 2024 | L77: 2-weeks treatment course
B78: Costs | D78: Chronic phase
B79: Costs | C79: n_reported_cases_chronic | D79: Total number of reported cases in chronic phase | E79: NA | F79: 2019 | G79: 20192 | H79: =(1-0.25)*G79 -> 15144 | I79: =(1+0.25)*G79 -> 25240 | J79: Gamma | K79: Gonçalves, et al. 2024
B80: Costs | C80: n_outpatient_visit_chronic | D80: Number of outpatient visits during the chronic phase | E80: NA | F80: NA | G80: 3 | H80: NA | I80: NA | J80: NA | K80: Assumption | L80: Once every 8 weeks (Table 4)
B81: Costs | C81: mild_illness_share_chronic | D81: Share of chronic phase cases with mild illness | E81: NA | F81: NA | G81: 0.404 | H81: =(1-0.25)*G81 -> 0.303 | I81: =(1+0.25)*G81 -> 0.505 | J81: Beta | K81: Gonçalves, et al. 2024; Delgado-Enciso I, Paz-Michel B, Melnikov V, Guzman-Esquivel J, Espinoza-Gomez F, Soriano-Hernandez AD, et al. Smoking and female sex as key risk factors associated with severe arthralgia in acute and chronic phases of Chikungunya virus infection. Exp Ther Med 2018; 15(3): 2634-42. https://doi.org/10.3892/etm.2017.5668 [DOI] [PMC free article] [PubMed]
B82: Costs | C82: C_hydroxychloroquine | D82: Cost of hydroxychloroquine (for the treatment of mild illness) | E82: BRL | F82: 2019 | G82: 244.78 | H82: =(1-0.25)*G82 -> 183.585 | I82: =(1+0.25)*G82 -> 305.975 | J82: Gamma | K82: Gonçalves, et al. 2024
B83: Costs | C83: C_methotrexate | D83: Cost of methotrexate (for the treatment of moderate/severe illness) | E83: BRL | F83: 2019 | G83: 109.86 | H83: =(1-0.25)*G83 -> 82.395 | I83: =(1+0.25)*G83 -> 137.325 | J83: Gamma | K83: Gonçalves, et al. 2024
B84: Costs | C84: C_folic_acid | D84: Cost of folic acid (for the treatment of moderate/severe illness) | E84: BRL | F84: 2019 | G84: 0.87 | H84: =(1-0.25)*G84 -> 0.6525 | I84: =(1+0.25)*G84 -> 1.0875 | J84: Gamma | K84: Gonçalves, et al. 2024
B85: Costs | D85: Indirect Costs
B86: Costs | C86: Work_Days_Lost | D86: Average working days lost | E86: NA | F86: NA | G86: 20.6 | H86: 11.8 | I86: 26.6 | J86: Gamma | K86: Bastos, et al. 2018. | L86: Bastos MLA, Abreu F de, Silva Junior G da, et al. Inability to work due to Chikungunya virus infection: impact on public service during the first epidemic in the State of Ceará, northeastern Brazil. Braz J Infect Dis 2018; 22:248–9. doi:10.1016/j.bjid.2018.05.002 and https://gh.bmj.com/content/9/12/e016648#T1
B87: Costs | C87: Abs_Days_Inf | D87: Absenteeism days, infectious phase | E87: NA | F87: NA | G87: 6.24 | H87: 0 | I87: 21 | J87: Gamma | K87: de Roo, et al. 2024 | L87: Feldstein LR, Ellis EM, Rowhani-Rahbar A, et al. Estimating the cost of illness and burden of disease associated with the 2014-2015 chikungunya outbreak in the U.S. Virgin Islands. PLoS Negl Trop Dis 2019; 13. doi:10.1371/journal.pntd.0007563
B88: Costs | C88: Abs_Freq_Inf | D88: Absenteeism frequency, infectious phase | E88: NA | F88: NA | G88: 0.89 | H88: 0.778 | I88: 1 | J88: Beta | K88: de Roo, et al. 2024 | L88: Feldstein LR, Ellis EM, Rowhani-Rahbar A, et al. Estimating the cost of illness and burden of disease associated with the 2014-2015 chikungunya outbreak in the U.S. Virgin Islands. PLoS Negl Trop Dis 2019; 13. doi:10.1371/journal.pntd.0007563
B89: Costs | C89: Abs_Freq_Chronic | D89: Absenteeism frequency, chronic phase | E89: NA | F89: NA | G89: 0.87 | H89: 0.784 | I89: 0.947 | J89: Beta | K89: de Roo, et al. 2024 | L89: Feldstein LR, Ellis EM, Rowhani-Rahbar A, et al. Estimating the cost of illness and burden of disease associated with the 2014-2015 chikungunya outbreak in the U.S. Virgin Islands. PLoS Negl Trop Dis 2019; 13. doi:10.1371/journal.pntd.0007563
B90: Costs | C90: GDP_Per_Capita | D90: GDP per capita | E90: BRL | F90: 2024 | G90: 55247.45 | H90: NA | I90: NA | J90: NA | K90: https://agenciadenoticias.ibge.gov.br/en/agencia-press-room/2185-news-agency/releases-en/42777-gdp-grows-3-4-in-2024-and-closes-the-year-at-r-11-7-trillion
B91: Costs | C91: C_Gross_Inc_month | D91: Average monthly real gross earnings | E91: BRL | F91: 2024 | G91: 3057 | H91: NA | I91: NA | J91: NA | K91: https://agenciadenoticias.ibge.gov.br/en/agencia-press-room/2185-news-agency/releases-en/42766-ibge-releases-per-capita-household-earnings-2024-for-brazil-and-federation-units
B92: Costs | C92: C_INSS_Rate | D92: Employee mandatory contribution (INSS) rate, share of gross income | E92: NA | F92: 2024 | G92: 0.2 | H92: NA | I92: NA | J92: NA | K92: https://www.gov.br/receitafederal/pt-br/assuntos/meu-imposto-de-renda/preenchimento/regimes
B93: Costs | C93: C_Simp_Ded_Rate | D93: Simplified deductions rate | E93: NA | F93: NA | G93: 0.2 | H93: NA | I93: NA | J93: NA | K93: https://izajole.springeropen.com/articles/10.1186/s40172-014-0014-0
B94: Costs | C94: C_Simp_Ded_Cap_year | D94: Annual cap for the simplified 20% option | E94: BRL | F94: 2024 | G94: 16754.34 | H94: NA | I94: NA | J94: NA | K94: https://www.gov.br/receitafederal/pt-br/assuntos/meu-imposto-de-renda/tabelas/copy_of_2024
B95: Costs | C95: Inf_Caregiving_Days_Inf | D95: Informal caregiving days, infectious phase | E95: NA | F95: NA | G95: 4.82 | H95: 2.08 | I95: 7.56 | J95: Gamma | K95: de Roo, et al. 2024 | L95: Mia MS, Begum RA, Er AC, et al. ASSESSING THE COST BURDEN OF DENGUE INFECTION TO HOUSEHOLDS IN SEREMBAN, MALAYSIA. Southeast Asian J Trop Med Public Health 2016;47:1167–76.
B96: Costs | C96: Inf_Caregiving_Freq_Inf | D96: Informal caregiving frequency, infectious phase | E96: NA | F96: NA | G96: 0.18 | H96: 0.169 | I96: 0.193 | J96: Beta | K96: de Roo, et al. 2024 | L96: Lindsey NP, Staples JE, Fischer M. Chikungunya Virus Disease among Travelers-United States, 2014-2016. Am J Trop Med Hyg 2018;98:192–7.
B97: Costs | C97: Inf_Caregiving_Days_Chronic | D97: Informal caregiving days, chronic phase | E97: NA | F97: NA | G97: 11.4 | H97: 9.13 | I97: 13.71 | J97: Gamma | K97: de Roo, et al. 2024 | L97: Verstappen SMM, Boonen A, Verkleij H, et al. Productivity costs among patients with rheumatoid arthritis: the influence of methods and sources to value loss of productivity. Ann Rheum Dis 2005;64:1754–60.
B98: Costs | C98: Inf_Caregiving_Freq_Chronic | D98: Informal caregiving frequency, chronic phase | E98: NA | F98: NA | G98: 0.34 | H98: 0.298 | I98: 0.375 | J98: Beta | K98: de Roo, et al. 2024 | L98: Verstappen SMM, Boonen A, Verkleij H, et al. Productivity costs among patients with rheumatoid arthritis: the influence of methods and sources to value loss of productivity. Ann Rheum Dis 2005;64:1754–60.
B99: Costs | C99: C_S | D99: Susceptible | E99: BRL | F99: 2024 | G99: 0 | H99: NA | I99: NA | J99: NA | K99: Assumption
B100: Costs | C100: C_V | D100: Vaccinated | E100: BRL | F100: 2024 | G100: 0 | H100: NA | I100: NA | J100: NA | K100: Assumption
...

Sheet Vaccine Efficacy >>

Sheet seroresponse
A1: measure | B1: days | C1: value | D1: lower | E1: upper | F1: vaccine | G1: source | H1: comments
A2: Seroprotection | B2: 29 | C2: 0.989 | D2: 0.967 | E2: 0.998 | F2: IXCHIQ | G2: Schneider et al. Lancet. 2023 | H2: Overall, Table 2
A3: Seroprotection | B3: 29 | C3: 0.991 | D3: 0.975 | E3: 0.998 | F3: IXCHIQ | G3: McMahon et al. Lancet ID. 2024 | H3: Overall; Figure 2
A4: Seroprotection | B4: =6*30.44 -> 182.64 | C4: 0.978 | D4: 0.956 | E4: 0.99 | F4: IXCHIQ | G4: McMahon et al. Lancet ID. 2024 | H4: Overall; Figure 2
A5: Seroprotection | B5: 365 | C5: 0.989 | D5: 0.972 | E5: 0.997 | F5: IXCHIQ | G5: McMahon et al. Lancet ID. 2024 | H5: Overall; Figure 2
A6: Seroprotection | B6: =+B5*2 -> 730 | C6: 0.968 | D6: 0.943 | E6: 0.985 | F6: IXCHIQ | G6: McMahon et al. Lancet ID. 2024 | H6: Overall; Figure 2
A7: Seroresponse rate differences | B7: 8 | C7: 0.461 | D7: 0.438 | E7: 0.481 | F7: VIMKUNYA | G7: Richardson JS, Anderson DM, Mendy J, Tindale LC, Muhammad S, Loreth T, Tredo SR, Warfield KL, Ramanathan R, Caso JT, Jenkins VA, Ajiboye P, Bedell L; EBSI-CV-317-004 Study Group. Chikungunya virus virus-like particle vaccine safety and immunogenicity in adolescents and adults in the USA: a phase 3, randomised, double-blind, placebo-controlled trial. Lancet. 2025 Apr 19;405(10487):1343-1352. doi: 10.1016/S0140-6736(25)00345-9. Epub 2025 Mar 27. PMID: 40158526. | H7: Table 2
A8: Seroresponse rate differences | B8: 15 | C8: 0.96 | D8: 0.943 | E8: 0.968 | F8: VIMKUNYA | G8: Richardson JS, Anderson DM, Mendy J, Tindale LC, Muhammad S, Loreth T, Tredo SR, Warfield KL, Ramanathan R, Caso JT, Jenkins VA, Ajiboye P, Bedell L; EBSI-CV-317-004 Study Group. Chikungunya virus virus-like particle vaccine safety and immunogenicity in adolescents and adults in the USA: a phase 3, randomised, double-blind, placebo-controlled trial. Lancet. 2025 Apr 19;405(10487):1343-1352. doi: 10.1016/S0140-6736(25)00345-9. Epub 2025 Mar 27. PMID: 40158526. | H8: Table 2
A9: Seroresponse rate differences | B9: 22 | C9: 0.966 | D9: 0.95 | E9: 0.975 | F9: VIMKUNYA | G9: Richardson JS, Anderson DM, Mendy J, Tindale LC, Muhammad S, Loreth T, Tredo SR, Warfield KL, Ramanathan R, Caso JT, Jenkins VA, Ajiboye P, Bedell L; EBSI-CV-317-004 Study Group. Chikungunya virus virus-like particle vaccine safety and immunogenicity in adolescents and adults in the USA: a phase 3, randomised, double-blind, placebo-controlled trial. Lancet. 2025 Apr 19;405(10487):1343-1352. doi: 10.1016/S0140-6736(25)00345-9. Epub 2025 Mar 27. PMID: 40158526. | H9: Table 2
A10: Seroresponse rate differences | B10: 183 | C10: 0.84 | D10: 0.817 | E10: 0.856 | F10: VIMKUNYA | G10: Richardson JS, Anderson DM, Mendy J, Tindale LC, Muhammad S, Loreth T, Tredo SR, Warfield KL, Ramanathan R, Caso JT, Jenkins VA, Ajiboye P, Bedell L; EBSI-CV-317-004 Study Group. Chikungunya virus virus-like particle vaccine safety and immunogenicity in adolescents and adults in the USA: a phase 3, randomised, double-blind, placebo-controlled trial. Lancet. 2025 Apr 19;405(10487):1343-1352. doi: 10.1016/S0140-6736(25)00345-9. Epub 2025 Mar 27. PMID: 40158526. | H10: Table 2

Sheet Demographics >>

Sheet life_tables
A2: BRASIL: Tábua Completa de Mortalidade - Ambos os Sexos – 2024
G3: (Continua)
A4: Idades | B4: Probabilidades de Morte | C4: Óbitos | D4: l ( X ) | E4: L (X, N) | F4: T(X) | G4: Expectativa de Vida
A5: Exatas | B5: entre Duas Idades Exatas | C5: D (X, N) | G5: à Idade X
A6: (X) | B6: Q (X, N) (Por Mil) | G6: E(X)
A7: age | B7: death_prob | G7: life_expectancy
A8: 0 | B8: 12.255129 | C8: 1225.5129 | D8: 100000 | E8: 98926.551 | F8: 7660788.4 | G8: 76.607884
A9: 1 | B9: 0.74460443 | C9: 73.547921 | D9: 98774.487 | E9: 98737.713 | F9: 7561861.8 | G9: 76.556832
A10: 2 | B10: 0.59254521 | C10: 58.484769 | D10: 98700.939 | E10: 98671.697 | F10: 7463124.1 | G10: 75.613506
A11: 3 | B11: 0.47361227 | C11: 46.718277 | D11: 98642.454 | E11: 98619.095 | F11: 7364452.4 | G11: 74.658041
A12: 4 | B12: 0.38209617 | C12: 37.673054 | D12: 98595.736 | E12: 98576.9 | F12: 7265833.3 | G12: 73.69318
A13: 5 | B13: 0.31305262 | C13: 30.853859 | D13: 98558.063 | E13: 98542.636 | F13: 7167256.4 | G13: 72.721157
A14: 6 | B14: 0.26253592 | C14: 25.866932 | D14: 98527.209 | E14: 98514.276 | F14: 7068713.8 | G14: 71.743773
A15: 7 | B15: 0.22730591 | C15: 22.389937 | D15: 98501.342 | E15: 98490.147 | F15: 6970199.5 | G15: 70.762482
A16: 8 | B16: 0.20513093 | C16: 20.201079 | D16: 98478.952 | E16: 98468.852 | F16: 6871709.4 | G16: 69.778457
A17: 9 | B17: 0.19482619 | C17: 19.182343 | D17: 98458.751 | E17: 98449.16 | F17: 6773240.5 | G17: 68.792671
A18: 10 | B18: 0.19662671 | C18: 19.355848 | D18: 98439.569 | E18: 98429.891 | F18: 6674791.3 | G18: 67.805979
A19: 11 | B19: 0.21238234 | C19: 20.902715 | D19: 98420.213 | E19: 98409.762 | F19: 6576361.5 | G19: 66.819216
... A97: 89 | B97: 128.8042 | C97: 3097.6415 | D97: 24049.227 | E97: 22500.407 | F97: 128385.23 | G97: 5.3384347
A98: 90 ou mais | B98: 1000 | C98: 20951.586 | D98: 20951.586 | E98: 105884.82 | F98: 105884.82 | G98: 5.0537856
A99: Fonte: IBGE, Diretoria de Pesquisas (DPE), Coordenação de População e Indicadores Sociais (COPIS).
A101: Notas:
A102: N = 1
A103: Q(X, N) = Probabilidades de morte entre as idades exatas X e X+N.
A104: l(X) = Número de sobreviventes à idade exata X.
A105: D(X, N) = Número de óbitos ocorridos entre as idades X e X+N.
A106: L(X, N) = Número de pessoas-anos vividos entre as idades X e X+N.
A107: T(X) = Número de pessoas-anos vividos a partir da idade X.
A108: E(X) = Expectativa de vida à idade X.

Sheet age_pyramid
A1: Age | B1: M | C1: F
A2: 0-4 | B2: 6682042 | C2: 6413556
A3: 45786 | B3: 7241538 | C3: 6953921
A4: 45944 | B4: 7342997 | C4: 7055760
A5: 15-19 | B5: 7575432 | C5: 7301316
A6: 20-24 | B6: 7970234 | C6: 7760334
A7: 25-29 | B7: 8241074 | C7: 8130717
A8: 30-34 | B8: 8048069 | C8: 8031559
A9: 35-39 | B9: 8293365 | C9: 8382279
A10: 40-44 | B10: 8156539 | C10: 8366021
A11: 45-49 | B11: 7272748 | C11: 7582165
A12: 50-54 | B12: 6366856 | C12: 6747807
A13: 55-59 | B13: 5724442 | C13: 6194348
A14: 60-64 | B14: 5084846 | C14: 5654490
A15: 65-69 | B15: 3993485 | C15: 4640221
A16: 70-74 | B16: 2877264 | C16: 3565249
... A22: 100+ | B22: 2629 | C22: 4986

Sheet Costs >>

Sheet tax_rates
A1: lower_taxable_income | B1: upper_taxable_income | C1: tax_rate | D1: parcela | E1: Source
A2: 0 | B2: 26963.2 | C2: 0 | D2: 0 | E2: https://www.gov.br/receitafederal/pt-br/assuntos/meu-imposto-de-renda/tabelas/copy_of_2024
A3: 26963.21 | B3: 33919.8 | C3: 0.075 | D3: 2022.24 | E3: https://www.gov.br/receitafederal/pt-br/assuntos/meu-imposto-de-renda/tabelas/copy_of_2024
A4: 33919.81 | B4: 45012.6 | C4: 0.15 | D4: 4566.23 | E4: https://www.gov.br/receitafederal/pt-br/assuntos/meu-imposto-de-renda/tabelas/copy_of_2024
A5: 45012.61 | B5: 55976.16 | C5: 0.225 | D5: 7942.17 | E5: https://www.gov.br/receitafederal/pt-br/assuntos/meu-imposto-de-renda/tabelas/copy_of_2024
A6: 55976.17 | B6: Inf | C6: 0.275 | D6: 10740.98 | E6: https://www.gov.br/receitafederal/pt-br/assuntos/meu-imposto-de-renda/tabelas/copy_of_2024

Sheet qdenga_price
B1: QDENGA ICER BY CONITEC - BRAZILIAN AGENCY
B4: Source: National Commission for the Incorporation of Technologies in the Unified Health System. (2023). Recommendation report No. 871: Tetravalent dengue vaccine (attenuated) for the prevention of infection caused by the dengue virus and its complications. Ministry of Health.
B6: PMVG without taxes | C6: PMVG 0% (R$) | D6: PMVG 18% (R$) | E6: Suggested price by Takeda for SUS (R$) | F6: Final price agreement (R$) | H6: Gap between final price and initial max price
B7: 157.35 | C7: 176.23 | D7: 220.83 | E7: 170 | F7: 95 | G7: =+F7/D7 -> 0.43019517 | H7: =1-G7 -> 0.56980483

Sheet pneumo-13_price
B7: PNEUMO-13 VACCINE
C12: PMVG 0% (R$) | D12: Suggested price by Pfizer for SUS (R$)
C13: 131.92 | D13: 63.85
G15: Although the vaccine had already been incorporated in 2019 for high-risk groups,
G16: it was in this 2023 report (attempt to substitute PCV10 with PCV13 for all children) that the offered price became explicit and significantly below the market price, consolidating the argument for government negotiation.
B27: Discount Aggressiveness: The Pfizzer offered the vaccine for R$ 63.85, which represents a discount of about 51%compared to the CMED ceiling price (R$ 131.92).
B28: Comparison with Current Prices: The offered value (R$ 63.85) was even lower than the price the government was already paying for the same vaccine for high-risk groups (CRIE), which was R$ 76.50.
B30: Disclosures
B31: Why was it not incorporated even with the discount? Despite the attractive price, Conitec recommended against incorporation based on three main pillars:
B33: 1.Hidden Logistics Costs: PCV13 is supplied in a pre-filled syringe (larger volume), while the current vaccine (PCV10) is a multidose vial. The change would generate an extra cost for logistics and storage (cold chain) estimated at more than R$ 16 million per year, which would "offset" part of the savings from the dose price.
B35: 2. Industrial Policy: The current vaccine (PCV10) is produced by Fiocruz (national) via technology transfer, ensuring self-sufficiency for the country.
B37: 3. Epidemiological Data: The Ministry of Health assessed that there was no epidemiological emergency justifying the switch, as severe cases remained stable.
B41: Source: National Commission for the Incorporation of Technologies in the Unified Health System. (2023).
B42: Recommendation report No. 819: 13-valent pneumococcal conjugate vaccine for immunization of children up to five years of age against invasive pneumococcal disease and pneumonia. Ministry of Health
B43: https://www.gov.br/conitec/pt-br/midias/relatorios/2023/20230710_relatorio_vacinapcv13_pneumo.pdf

Sheet chiqx_price
B1: CHICUNGUNYA BRAZIL LEGAL PRICE
B3: Source: CMED (https://www.gov.br/anvisa/pt-br/assuntos/medicamentos/cmed/precos)
B5: ICMS % (tax)* | C5: PMVG (Max Gov Price, R$) | D5: PMC (Max Consumer Price, R$) | E5: PMVG (USD) | F5: PMC (USD)
B6: 0 | C6: 761.88 | D6: 1022.03 | E6: =C6/5.66 -> 134.60777 | F6: =D6/5.66 -> 180.57067
B7: 0.12 | C7: 865.77 | D7: 1161.4 | E7: =C7/5.66 -> 152.9629 | F7: =D7/5.66 -> 205.19435 | I7: BRL | J7: BRL
B8: 0.17 | C8: 917.93 | D8: 1231.37 | E8: =C8/5.66 -> 162.17845 | F8: =D8/5.66 -> 217.55654 | I8: Public | J8: Private | M8: Base | N8: LB | O8: UB
B9: 0.175 | C9: 923.49 | D9: 1238.83 | E9: =C9/5.66 -> 163.16078 | F9: =D9/5.66 -> 218.87456 | H9: LB | I9: =+C6 -> 761.88 | J9: =+D6 -> 1022.03 | L9: Public | M9: =I10 -> 929.12 | N9: =I9 -> 761.88 | O9: =I11 -> 989.45
B10: 0.18 | C10: 929.12 | D10: 1246.38 | E10: =C10/5.66 -> 164.15548 | F10: =D10/5.66 -> 220.20848 | H10: Base | I10: =+C10 -> 929.12 | J10: =+D10 -> 1246.38 | L10: Private | M10: =J10 -> 1246.38 | N10: =J9 -> 1022.03 | O10: =J11 -> 1327.31
B11: 0.19 | C11: 940.59 | D11: 1261.77 | E11: =C11/5.66 -> 166.18198 | F11: =D11/5.66 -> 222.92756 | H11: UB | I11: =+C18 -> 989.45 | J11: =+D18 -> 1327.31
B12: 0.195 | C12: 946.43 | D12: 1269.61 | E12: =C12/5.66 -> 167.21378 | F12: =D12/5.66 -> 224.31272
B13: 0.2 | C13: 952.35 | D13: 1277.54 | E13: =C13/5.66 -> 168.25972 | F13: =D13/5.66 -> 225.71378
B14: 0.205 | C14: 958.34 | D14: 1285.58 | E14: =C14/5.66 -> 169.31802 | F14: =D14/5.66 -> 227.13428
B15: 0.21 | C15: 964.41 | D15: 1293.72 | E15: =C15/5.66 -> 170.39046 | F15: =D15/5.66 -> 228.57244
B16: 0.22 | C16: 976.77 | D16: 1310.3 | E16: =C16/5.66 -> 172.5742 | F16: =D16/5.66 -> 231.50177
B17: 0.225 | C17: 983.07 | D17: 1318.75 | E17: =C17/5.66 -> 173.68728 | F17: =D17/5.66 -> 232.9947
B18: 0.23 | C18: 989.45 | D18: 1327.31 | E18: =C18/5.66 -> 174.81449 | F18: =D18/5.66 -> 234.50707
B20: * Depending on the region (State of Brazil), taxes can reach 23%.
B21: US = 5,66 REAIS
B23: Term Meaning
B24: PMVG Maximum Selling Price to the Government – ​​is the highest price at which a medicine can be sold to public bodies and entities. It is used as a reference in purchases by the SUS (Brazilian Public Health System), Ministry of Health, states and municipalities.
B26: PMC Maximum Price to the Consumer – is the price ceiling that private pharmacies and hospitals can charge the final consumer. It varies according to the ICMS (Brazilian state sales tax) of each state.
B28: The maximum price varies according to the taxes in each region. Taxes range from 0% to 23% and it has an impact on price. This is not the final price that can be used for incorporation into the Brazilian public health system.
B30: Using the price of the Qdenga vaccine as a proxy is interesting because it was the price incorporated into the public health system, which was well below that established by CMED.
B32: 18% is usually choose as a reference for CONITEC calculation for ICER analysis

Sheet calculations
B2: Vaccine | C2: Manufacturer | D2: Year | E2: Comments | F2: PMVG without taxes | G2: PMVG 0% (R$) | H2: PMVG 18% (R$) | I2: Manufacturer Price for SUS (R$) | J2: Final price agreement (R$) | K2: Price Discount
B3: QDENGA | C3: Takeda | D3: 2025 | E3: Planned for implementation | F3: =qdenga_price!B7 -> 157.35 | G3: =qdenga_price!C7 -> 176.23 | H3: =qdenga_price!D7 -> 220.83 | I3: =qdenga_price!E7 -> 170 | J3: =qdenga_price!F7 -> 95 | K3: =1-J3/H3 -> 0.56980483
B4: Pneumo13 | C4: Pfizer | D4: 2023 | E4: Not implemented | G4: ='pneumo-13_price'!$C$13 -> 131.92 | H4: =+(H3/G3)*G4 -> 165.3061 | I4: ='pneumo-13_price'!$D$13 -> 63.85 | J4: 76.75 | K4: =1-J4/H4 -> 0.53570981

Sheet Adjustments >>

Sheet cpi
A1: observation_date | B1: BRACPIALLMINMEI | E1: FRED Graph Observations
A2: 29190 | B2: 1.767538e-10 | E2: Federal Reserve Economic Data, Federal Reserve Bank of St. Louis
A3: 29221 | B3: 1.884472e-10 | E3: Link: https://fred.stlouisfed.org
A4: 29252 | B4: 1.971477e-10 | E4: Help: https://fredhelp.stlouisfed.org
A5: 29281 | B5: 2.090522e-10 | E5: This data may be copyrighted. Please refer to the Terms of Use: https://fred.stlouisfed.org/legal#fred-terms-faq
A6: 29312 | B6: 2.201029e-10 | E6: File Created: 2025-12-19 8:51 pm CST
A7: 29342 | B7: 2.326548e-10
A8: 29373 | B8: 2.449979e-10 | E8: BRACPIALLMINMEI | F8: Consumer Price Indices (CPIs, HICPs), COICOP 1999: Consumer Price Index: Total for Brazil, Index 2015=100, Monthly, Not Seasonally Adjusted | G8: Data Updated: 2025-05-15
A9: 29403 | B9: 2.585845e-10 | E9: https://fred.stlouisfed.org/series/BRACPIALLMINMEI
A10: 29434 | B10: 2.71373e-10
A11: 29465 | B11: 2.82853e-10
A12: 29495 | B12: 3.096689e-10
A13: 29526 | B13: 3.303343e-10
A14: 29556 | B14: 3.521828e-10
A15: 29587 | B15: 3.762634e-10
A16: 29618 | B16: 4.003486e-10
A17: 29646 | B17: 4.202529e-10
A18: 29677 | B18: 4.474099e-10
A19: 29707 | B19: 4.722839e-10
A20: 29738 | B20: 4.983435e-10
A21: 29768 | B21: 5.29519e-10
... A373: 40483 | B373: 73.68427
A374: 40513 | B374: 74.14853 | C374: =AVERAGE(B363:B374) -> 72.260279
A375: 40544 | B375: 74.76406
A376: 40575 | B376: 75.36218
A377: 40603 | B377: 75.95753
A378: 40634 | B378: 76.54243
A379: 40664 | B379: 76.90228
A380: 40695 | B380: 77.01759
A381: 40725 | B381: 77.14079
A382: 40756 | B382: 77.42616
A383: 40787 | B383: 77.83659
A384: 40817 | B384: 78.17139
A385: 40848 | B385: 78.57787
A386: 40878 | B386: 78.97067 | C386: =AVERAGE(B375:B386) -> 77.055795
A387: 40909 | B387: 79.41289
A388: 40940 | B388: 79.77019
A389: 40969 | B389: 79.9377
A390: 41000 | B390: 80.44929
A391: 41030 | B391: 80.73884
A392: 41061 | B392: 80.80334
A393: 41091 | B393: 81.15089
A394: 41122 | B394: 81.4836
A395: 41153 | B395: 81.94808
A396: 41183 | B396: 82.43159
A397: 41214 | B397: 82.92625
A398: 41244 | B398: 83.58145 | C398: =AVERAGE(B387:B398) -> 81.219509
A399: 41275 | B399: 84.30022
A400: 41306 | B400: 84.80601
A401: 41334 | B401: 85.20461
A402: 41365 | B402: 85.67327
A403: 41395 | B403: 85.9902
A404: 41426 | B404: 86.21386
A405: 41456 | B405: 86.23961
A406: 41487 | B406: 86.44656
A407: 41518 | B407: 86.74911
A408: 41548 | B408: 87.24353
A409: 41579 | B409: 87.71474
A410: 41609 | B410: 88.52168 | C410: =AVERAGE(B399:B410) -> 86.258617
A411: 41640 | B411: 89.00845
A412: 41671 | B412: 89.62258
A413: 41699 | B413: 90.44715
A414: 41730 | B414: 91.05317
A415: 41760 | B415: 91.47195
A416: 41791 | B416: 91.83783
A417: 41821 | B417: 91.84711
A418: 41852 | B418: 92.07681
A419: 41883 | B419: 92.60162
A420: 41913 | B420: 92.99047
A421: 41944 | B421: 93.4647
A422: 41974 | B422: 94.19368 | C422: =AVERAGE(B411:B422) -> 91.71796
A423: 42005 | B423: 95.36163
A424: 42036 | B424: 96.52494
A425: 42064 | B425: 97.79915
A426: 42095 | B426: 98.49356
A427: 42125 | B427: 99.22231
A428: 42156 | B428: 100.0063
A429: 42186 | B429: 100.6262
A430: 42217 | B430: 100.8476
A431: 42248 | B431: 101.3921
A432: 42278 | B432: 102.2234
A433: 42309 | B433: 103.2558
A434: 42339 | B434: 104.247 | C434: =AVERAGE(B423:B434) -> 99.999999
A435: 42370 | B435: 105.5709
A436: 42401 | B436: 106.521
A437: 42430 | B437: 106.9789
A438: 42461 | B438: 107.6316
A439: 42491 | B439: 108.471
A440: 42522 | B440: 108.8506
A441: 42552 | B441: 109.4167
A442: 42583 | B442: 109.8981
A443: 42614 | B443: 109.9861
A444: 42644 | B444: 110.2721
A445: 42675 | B445: 110.4707
A446: 42705 | B446: 110.802 | C446: =AVERAGE(B435:B446) -> 108.73914
A447: 42736 | B447: 111.2231
A448: 42767 | B448: 111.5902
A449: 42795 | B449: 111.8691
A450: 42826 | B450: 112.0257
A451: 42856 | B451: 112.373
...

Sheet spot_fx_rate
A1: observation_date | B1: AEXBZUS
A2: 34700 | B2: 0.9161
A3: 35065 | B3: 1.0051
A4: 35431 | B4: 1.0779
A5: 35796 | B5: 1.1605
A6: 36161 | B6: 1.8207
A7: 36526 | B7: 1.8301
A8: 36892 | B8: 2.3527
A9: 37257 | B9: 2.9213
A10: 37622 | B10: 3.075
A11: 37987 | B11: 2.9262
A12: 38353 | B12: 2.4352
A13: 38718 | B13: 2.1738
... A31: 45292 | B31: 5.3872
A35: https://fred.stlouisfed.org/series/AEXBZUS
A36: FRED Graph Observations
A37: Federal Reserve Economic Data, Federal Reserve Bank of St. Louis
A38: Link: https://fred.stlouisfed.org
A39: Help: https://fredhelp.stlouisfed.org
A40: This data may be copyrighted. Please refer to the Terms of Use: https://fred.stlouisfed.org/legal#fred-terms-faq
A41: File Created: 2025-11-17 3:28 pm CST
A43: AEXBZUS | B43: Brazilian Reals to U.S. Dollar Spot Exchange Rate, Brazilian Reals to One U.S. Dollar, Annual, Not Seasonally Adjusted | C43: Data Updated: 2025-01-03
